{
  "contactInfo": [
    {
      "icon": "Mail",
      "label": "Email",
      "value": "puskarsaha3@gmail.com",
      "href": "mailto:puskarsaha3@gmail.com"
    },
    {
      "icon": "Phone",
      "label": "Phone",
      "value": "(+91) 9734071136",
      "href": "tel:+919734071136"
    },
    {
      "icon": "MapPin",
      "label": "Location",
      "value": "Katwa, West Bengal, India",
      "href": null
    }
  ],
  "socialLinks": [
    {
      "icon": "Github",
      "label": "GitHub",
      "href": "https://github.com/PUSKAR-DJ"
    },
    {
      "icon": "Linkedin",
      "label": "LinkedIn",
      "href": "https://linkedin.com/in/puskarsaha3"
    },
    {
      "icon": "Twitter",
      "label": "Twitter",
      "href": "https://www.x.com/PUSKAR_DJ"
    }
  ]
}